jdSimpleAutostart/AddEditDialog.py
jdSimpleAutostart/AddMenuDialog.py
jdSimpleAutostart/Functions.py
jdSimpleAutostart/Icon.png
jdSimpleAutostart/MainWindow.py
jdSimpleAutostart/__init__.py
jdSimpleAutostart/__main__.py
jdSimpleAutostart/translations/jdSimpleAutostart_de.qm
jdSimpleAutostart/translations/jdSimpleAutostart_nl.qm
jdSimpleAutostart/translations/jdSimpleAutostart_ru.qm
jdSimpleAutostart/translations/jdSimpleAutostart_uk.qm
jdSimpleAutostart/ui_compiled/AddEditDialog.py
jdSimpleAutostart/ui_compiled/AddMenuDialog.py
jdSimpleAutostart/ui_compiled/MainWindow.py
jdSimpleAutostart/ui_compiled/__init__.py
jdsimpleautostart-1.5.dist-info/licenses/LICENSE
jdsimpleautostart-1.5.dist-info/METADATA
jdsimpleautostart-1.5.dist-info/WHEEL
jdsimpleautostart-1.5.dist-info/entry_points.txt
jdsimpleautostart-1.5.dist-info/top_level.txt
jdsimpleautostart-1.5.dist-info/RECORD
