Metadata-Version: 2.4
Name: jdSimpleAutostart
Version: 1.5
Summary: Edit autostart entries on Linux
Author-email: JakobDev <jakobdev@gmx.de>
License: GPL-3
Project-URL: Source, https://codeberg.org/JakobDev/jdFlatpakSnaphot
Project-URL: Issues, https://codeberg.org/JakobDev/jdFlatpakSnapshot/issues
Project-URL: Translate, https://translate.codeberg.org/projects/jdSimpleAutostart
Project-URL: Donation, https://ko-fi.com/jakobdev
Keywords: JakobDev,Linux,Freedesktop
Classifier: Development Status :: 5 - Production/Stable
Classifier: Intended Audience :: Developers
Classifier: Intended Audience :: End Users/Desktop
Classifier: Environment :: Other Environment
Classifier: Environment :: X11 Applications :: Qt
Classifier: License :: OSI Approved :: GNU General Public License v3 (GPLv3)
Classifier: Natural Language :: English
Classifier: Natural Language :: German
Classifier: Topic :: Software Development
Classifier: Topic :: Utilities
Classifier: Operating System :: POSIX
Classifier: Operating System :: POSIX :: BSD
Classifier: Operating System :: POSIX :: Linux
Classifier: Programming Language :: Python :: 3
Classifier: Programming Language :: Python :: 3.9
Classifier: Programming Language :: Python :: 3.10
Classifier: Programming Language :: Python :: 3.11
Classifier: Programming Language :: Python :: 3.12
Classifier: Programming Language :: Python :: 3.13
Classifier: Programming Language :: Python :: 3 :: Only
Classifier: Programming Language :: Python :: Implementation :: CPython
Requires-Python: >=3.9
License-File: LICENSE
Requires-Dist: PyQt6
Requires-Dist: desktop-entry-lib
Dynamic: license-file
